Workbook

Sheet Precios_Impuestos
A1: Producto | B1: Precio_Base | C1: Impuesto | D1: Precio_Final | E1: Descuento | F1: 0.07 | G1: Costo | H1: Margen | I1: Utilidad
A2: Producto 1 | B2: 50.13 | C2: =$F$1 -> 0.07 | D2: =B2*(1+$F$1) -> 53.6391 | E2: 0.11 | F2: =D2*(1-E2) -> 47.738799 | G2: 31.66 | H2: =D2-G2 -> 21.9791 | I2: =F2-G2 -> 16.078799
A3: Producto 2 | B3: 92.72 | C3: =$F$1 -> 0.07 | D3: =B3*(1+$F$1) -> 99.2104 | E3: 0.14 | F3: =D3*(1-E3) -> 85.320944 | G3: 39.56 | H3: =D3-G3 -> 59.6504 | I3: =F3-G3 -> 45.760944
A4: Producto 3 | B4: 68.8 | C4: =$F$1 -> 0.07 | D4: =B4*(1+$F$1) -> 73.616 | E4: 0.16 | F4: =D4*(1-E4) -> 61.83744 | G4: 13.56 | H4: =D4-G4 -> 60.056 | I4: =F4-G4 -> 48.27744
A5: Producto 4 | B5: 62.76 | C5: =$F$1 -> 0.07 | D5: =B5*(1+$F$1) -> 67.1532 | E5: 0.16 | F5: =D5*(1-E5) -> 56.408688 | G5: 5.1 | H5: =D5-G5 -> 62.0532 | I5: =F5-G5 -> 51.308688
A6: Producto 5 | B6: 69.67 | C6: =$F$1 -> 0.07 | D6: =B6*(1+$F$1) -> 74.5469 | E6: 0.15 | F6: =D6*(1-E6) -> 63.364865 | G6: 34.61 | H6: =D6-G6 -> 39.9369 | I6: =F6-G6 -> 28.754865
A7: Producto 6 | B7: 91.7 | C7: =$F$1 -> 0.07 | D7: =B7*(1+$F$1) -> 98.119 | E7: 0.19 | F7: =D7*(1-E7) -> 79.47639 | G7: 23.99 | H7: =D7-G7 -> 74.129 | I7: =F7-G7 -> 55.48639
A8: Producto 7 | B8: 50.99 | C8: =$F$1 -> 0.07 | D8: =B8*(1+$F$1) -> 54.5593 | E8: 0.16 | F8: =D8*(1-E8) -> 45.829812 | G8: 17.22 | H8: =D8-G8 -> 37.3393 | I8: =F8-G8 -> 28.609812
A9: Producto 8 | B9: 63.33 | C9: =$F$1 -> 0.07 | D9: =B9*(1+$F$1) -> 67.7631 | E9: 0.13 | F9: =D9*(1-E9) -> 58.953897 | G9: 27.42 | H9: =D9-G9 -> 40.3431 | I9: =F9-G9 -> 31.533897
A10: Producto 9 | B10: 10.65 | C10: =$F$1 -> 0.07 | D10: =B10*(1+$F$1) -> 11.3955 | E10: 0.06 | F10: =D10*(1-E10) -> 10.71177 | G10: 6.64 | H10: =D10-G10 -> 4.7555 | I10: =F10-G10 -> 4.07177
A11: Producto 10 | B11: 25.57 | C11: =$F$1 -> 0.07 | D11: =B11*(1+$F$1) -> 27.3599 | E11: 0.13 | F11: =D11*(1-E11) -> 23.803113 | G11: 45.91 | H11: =D11-G11 -> -18.5501 | I11: =F11-G11 -> -22.106887

Sheet Reporte
A1: Métrica | B1: Valor
A2: Total de Ventas | B2: =SUM(Precios_Impuestos!D2:D11) -> 627.3624
A3: Total de Descuentos Aplicados | B3: =SUM(Precios_Impuestos!D2:D11)-SUM(Precios_Impuestos!F2:F11) -> 93.916682
A4: Total de Costos | B4: =SUM(Precios_Impuestos!G2:G11) -> 245.67
A5: Utilidad Total | B5: =SUM(Precios_Impuestos!I2:I11) -> 287.77572
A6: Margen Promedio | B6: =AVERAGE(Precios_Impuestos!H2:H11) -> 38.16924
